pythologo/__init__.py
pythologo-0.1.dist-info/LICENSE.txt
pythologo-0.1.dist-info/METADATA
pythologo-0.1.dist-info/WHEEL
pythologo-0.1.dist-info/top_level.txt
pythologo-0.1.dist-info/RECORD
