Metadata-Version: 2.1
Name: pythologo
Version: 0.1
Summary: An animated python logo(to use only in google colab)
Author: vkr
Author-email: rakalyanram@gmail.com
Classifier: Programming Language :: Python :: 3
Classifier: License :: OSI Approved :: MIT License
Classifier: Operating System :: OS Independent
License-File: LICENSE.txt
